torch_lib/__init__.py
torch_lib/callback/__init__.py
torch_lib/callback/common.py
torch_lib/core/__init__.py
torch_lib/core/context.py
torch_lib/core/handler.py
torch_lib/core/status.py
torch_lib/data/__init__.py
torch_lib/log/__init__.py
torch_lib/log/directory.py
torch_lib/metric/__init__.py
torch_lib/module/__init__.py
torch_lib/module/config.py
torch_lib/util/__init__.py
torch_lib/util/formatter.py
torch_lib/util/table.py
torch_lib/util/terminal.py
torch_lib/util/type.py
torch_lib-0.3.4.dist-info/LICENSE
torch_lib-0.3.4.dist-info/METADATA
torch_lib-0.3.4.dist-info/WHEEL
torch_lib-0.3.4.dist-info/top_level.txt
torch_lib-0.3.4.dist-info/RECORD
