Metadata-Version: 2.1
Name: torch-lib
Version: 0.3.4
Summary: a pytorch lib that helps you to quickly write your training code
Home-page: https://github.com/johncaged/torch-lib
Author: Zikang Liu
Author-email: 573697439@qq.com
License: GNU General Public License v2.0
Platform: UNKNOWN
License-File: LICENSE
